rpcgrid/__init__.py
rpcgrid/client.py
rpcgrid/rpcgrid.py
rpcgrid/server.py
rpcgrid/task.py
rpcgrid/version.py
rpcgrid/aio/__init__.py
rpcgrid/aio/client.py
rpcgrid/aio/rpcgrid.py
rpcgrid/aio/server.py
rpcgrid/aio/task.py
rpcgrid/aio/providers/__init__.py
rpcgrid/aio/providers/base.py
rpcgrid/aio/providers/local.py
rpcgrid/aio/providers/rabbit.py
rpcgrid/aio/providers/socket.py
rpcgrid/protocol/__init__.py
rpcgrid/protocol/jsonrpc.py
rpcgrid/providers/__init__.py
rpcgrid/providers/base.py
rpcgrid/providers/local.py
rpcgrid/providers/socket.py
rpcgrid-0.0.1.dist-info/LICENSE.txt
rpcgrid-0.0.1.dist-info/METADATA
rpcgrid-0.0.1.dist-info/WHEEL
rpcgrid-0.0.1.dist-info/top_level.txt
rpcgrid-0.0.1.dist-info/RECORD
